MANIFEST.in
README.rst
setup.py
rxjson/Rx.py
rxjson/__init__.py
rxjson.egg-info/PKG-INFO
rxjson.egg-info/SOURCES.txt
rxjson.egg-info/dependency_links.txt
rxjson.egg-info/not-zip-safe
rxjson.egg-info/top_level.txt