Metadata-Version: 1.1
Name: rxjson
Version: 0.3
Summary: JSON RX Schema validation tool
Home-page: https://github.com/spiral-project/rxjson
Author: Rémy Hubscher
Author-email: hubscher.remy@gmail.com
License: GPLv2.0
Keywords: j,s,o,n, ,s,c,h,e,m,a, ,v,a,l,i,d,a,t,i,o,n, ,r,x, ,r,x,j,s,o,n
Platform: UNKNOWN
Classifier: Development Status :: 5 - Production/Stable
Classifier: Programming Language :: Python
Classifier: Programming Language :: Python :: 3
Classifier: Intended Audience :: Developers
Classifier: Topic :: Internet :: WWW/HTTP :: WSGI :: Application
Classifier: License :: OSI Approved :: GNU General Public License v2 (GPLv2)
